InstagramCLI/__init__.py
InstagramCLI-1.0.19.dist-info/LICENSE
InstagramCLI-1.0.19.dist-info/METADATA
InstagramCLI-1.0.19.dist-info/WHEEL
InstagramCLI-1.0.19.dist-info/top_level.txt
InstagramCLI-1.0.19.dist-info/RECORD
