Metadata-Version: 2.1
Name: InstagramCLI
Version: 1.0.19
Summary: CLI Tool made by reverse engineering Instagram API Calls.
Home-page: https://github.com/suyashjawale/InstagramCLI
Author: Suyash Jawale
Author-email: suyashjawale245@gmail.com
Keywords: instagram,instagramapi,instagramcli,api,instagram scraper,bot
Classifier: License :: OSI Approved :: MIT License
Classifier: Intended Audience :: Information Technology
Classifier: Intended Audience :: Developers
Classifier: Programming Language :: Python :: 3.6
Classifier: Programming Language :: Python :: 3.7
Classifier: Programming Language :: Python :: 3.8
Classifier: Programming Language :: Python :: 3.9
Classifier: Programming Language :: Python :: 3.10
Classifier: Topic :: Software Development :: Libraries :: Python Modules
Classifier: Operating System :: Microsoft :: Windows
Requires-Python: >=3.6
License-File: LICENSE
Requires-Dist: requests
Requires-Dist: bs4
